madeleine/__init__.py
madeleine/base.py
madeleine/generator.py
madeleine/helpers.py
madeleine/multiple.py
madeleine-0.1.0.dist-info/LICENSE
madeleine-0.1.0.dist-info/METADATA
madeleine-0.1.0.dist-info/WHEEL
madeleine-0.1.0.dist-info/top_level.txt
madeleine-0.1.0.dist-info/RECORD
