Metadata-Version: 2.1
Name: madeleine
Version: 0.1.0
Summary: Configurable random text generation
Home-page: https://gitlab.com/Lucidiot/madeleine
Author: Lucidiot
License: GNU General Public License 3
Project-URL: Source Code, https://gitlab.com/Lucidiot/madeleine
Project-URL: Bug Tracker, https://gitlab.com/Lucidiot/madeleine/issues
Project-URL: GitHub Mirror, https://github.com/Lucidiot/madeleine
Keywords: random text generation
Platform: UNKNOWN
Classifier: Development Status :: 3 - Alpha
Classifier: License :: OSI Approved :: GNU General Public License v3 (GPLv3)
Classifier: Natural Language :: English
Classifier: Intended Audience :: Developers
Classifier: Operating System :: OS Independent
Classifier: Programming Language :: Python :: 3
Classifier: Programming Language :: Python :: 3 :: Only
Classifier: Programming Language :: Python :: 3.5
Classifier: Programming Language :: Python :: 3.6
Classifier: Programming Language :: Python :: 3.7
Classifier: Topic :: Software Development :: Libraries
Classifier: Topic :: Text Processing
Classifier: Topic :: Utilities
Requires-Python: >=3.5
Requires-Dist: objtools (>=0.1)
Provides-Extra: dev
Requires-Dist: flake8 (>=3.5) ; extra == 'dev'
Requires-Dist: doc8 (>=0.8.0) ; extra == 'dev'
Requires-Dist: Sphinx (>=1.8.1) ; extra == 'dev'
Requires-Dist: coverage (>=4.5) ; extra == 'dev'
Requires-Dist: codecov (>=2.0) ; extra == 'dev'
Provides-Extra: toml
Requires-Dist: toml (>=0.10) ; extra == 'toml'
Provides-Extra: yaml
Requires-Dist: pyyaml (>=5.1) ; extra == 'yaml'
